aup_manager/__init__.py
aup_manager/api.py
aup_manager/app_properties.py
aup_manager/config-template.yaml
aup_manager/flask_app.py
aup_manager/gui.py
aup_manager/models.py
aup_manager/openapi-specification.yaml
aup_manager/connectors/ConnectorInterface.py
aup_manager/connectors/MongodbConnector.py
aup_manager/connectors/PerunConnector.py
aup_manager/connectors/SqlAlchemyConnector.py
aup_manager/connectors/__init__.py
aup_manager/db/DatabaseInterface.py
aup_manager/db/MongodbDatabase.py
aup_manager/db/SqlAlchemyDatabase.py
aup_manager/db/__init__.py
aup_manager/static/index.js
aup_manager/static/package-lock.json
aup_manager/static/package.json
aup_manager/static/assets/caret-down-solid.svg
aup_manager/static/scss/_stepper.scss
aup_manager/static/scss/custom.scss
aup_manager/templates/accept_aups.html
aup_manager/templates/aup_overview.html
aup_manager/templates/base.html
aup_manager/templates/create_aup.html
aup_manager/templates/login.html
aup_manager/templates/manage_aups.html
aup_manager/templates/text_message.html
aup_manager/templates/unauthorized.html
aup_manager-2.2.3.dist-info/LICENSE
aup_manager-2.2.3.dist-info/METADATA
aup_manager-2.2.3.dist-info/WHEEL
aup_manager-2.2.3.dist-info/top_level.txt
aup_manager-2.2.3.dist-info/RECORD
